README.txt
setup.py
django_dynamic_manipulation.egg-info/PKG-INFO
django_dynamic_manipulation.egg-info/SOURCES.txt
django_dynamic_manipulation.egg-info/dependency_links.txt
django_dynamic_manipulation.egg-info/not-zip-safe
django_dynamic_manipulation.egg-info/requires.txt
django_dynamic_manipulation.egg-info/top_level.txt
dynamic_manipulation/__init__.py
dynamic_manipulation/dynamic_actions.py
dynamic_manipulation/models.py
dynamic_manipulation/migrations/0001_initial.py
dynamic_manipulation/migrations/__init__.py
dynamic_manipulation/tests/__init__.py
dynamic_manipulation/tests/test_dynamic_actions.py
example/sample/__init__.py
example/sample/dynamic_actions.py
example/sample/models.py
example/sample/features/__init__.py
example/sample/features/manipulation_steps.py
example/sample/features/terrain.py