Metadata-Version: 1.0
Name: django-dynamic-manipulation
Version: 0.0.7
Summary: Record rule based dynamic manipulations.
Home-page: https://github.com/imtapps/django-dynamic-manipulation
Author: Matthew J Morrison & Aaron Madison
Author-email: mattjmorrison@mattjmorrison.com
License: UNKNOWN
Platform: UNKNOWN
Classifier: Development Status :: 3 - Alpha
Classifier: Environment :: Web Environment
Classifier: Framework :: Django
Classifier: Intended Audience :: Developers
Classifier: License :: OSI Approved :: BSD License
Classifier: Operating System :: OS Independent
Classifier: Programming Language :: Python
Classifier: Topic :: Software Development
Classifier: Topic :: Software Development :: Libraries :: Application Frameworks
